setup.py
au_dsnd_probability/Binomialdistribution.py
au_dsnd_probability/Gaussiandistribution.py
au_dsnd_probability/Generaldistribution.py
au_dsnd_probability/__init__.py
au_dsnd_probability.egg-info/PKG-INFO
au_dsnd_probability.egg-info/SOURCES.txt
au_dsnd_probability.egg-info/dependency_links.txt
au_dsnd_probability.egg-info/not-zip-safe
au_dsnd_probability.egg-info/top_level.txt