Metadata-Version: 2.1
Name: au-dsnd-probability
Version: 0.1
Summary: Gaussian, Binomial and Generic distributions
Author: Umar Abubakar
Author-email: uacoolbreeze@gmail.com
License: UNKNOWN
Platform: UNKNOWN
